print_schema/__init__.py
print_schema/print_schema.py
print_schema/run_print_schema.py
print_schema-1.1.1.dist-info/LICENSE
print_schema-1.1.1.dist-info/METADATA
print_schema-1.1.1.dist-info/WHEEL
print_schema-1.1.1.dist-info/top_level.txt
print_schema-1.1.1.dist-info/RECORD
