Metadata-Version: 2.1
Name: print-schema
Version: 1.1.1
Summary: Prints the schema of Python objects
Home-page: https://github.com/suryashekharc/print_schema
Author: Surya Shekhar Chakraborty
Author-email: suryaschak@gmail.com
License: MIT
Platform: UNKNOWN
Requires-Python: >=3.5
Requires-Dist: requests
